pyxelunicode/PyxelUnicode.py
pyxelunicode/__init__.py
pyxelunicode-1.0.4.dist-info/LICENSE
pyxelunicode-1.0.4.dist-info/METADATA
pyxelunicode-1.0.4.dist-info/WHEEL
pyxelunicode-1.0.4.dist-info/top_level.txt
pyxelunicode-1.0.4.dist-info/RECORD
