Metadata-Version: 2.1
Name: pyxelunicode
Version: 1.0.4
Summary: A pixel font builder for the game engine pyxel
Home-page: https://github.com/AceBee007/PyxelUnicode
Author: AceBee007
Author-email: acebee007github.robinia@slmail.me
License: UNKNOWN
Platform: UNKNOWN
Classifier: Programming Language :: Python :: 3
Classifier: License :: OSI Approved :: GNU General Public License v3 (GPLv3)
Classifier: Operating System :: OS Independent
Requires-Python: >=3.6
